pydantic_djmodel/__init__.py
pydantic_djmodel/_settings.py
pydantic_djmodel/core.py
pydantic_djmodel/py.typed
pydantic_djmodel-0.1.0.dist-info/LICENSE
pydantic_djmodel-0.1.0.dist-info/METADATA
pydantic_djmodel-0.1.0.dist-info/WHEEL
pydantic_djmodel-0.1.0.dist-info/RECORD
